excel2db/__init__.py
excel2db/astCode.py
excel2db/cheakConf.py
excel2db/defaultConf.py
excel2db/detailData.py
excel2db/detailTitle.py
excel2db/excel.py
excel2db/excel2db.py
excel2db/insert2sqlite.py
excel2db/mainData.py
excel2db/mainTitle.py
excel2db/scale.py
excel2db/sheet.py
excel2db/value.py
excel2db/com/__init__.py
excel2db/com/util/__init__.py
excel2db/com/util/coordinate.py
excel2db/com/util/dbconnect.py
excel2db/com/util/excelTool.py
excel2db/com/util/fileTool.py
excel2db/com/util/timeTool.py
excel2db/demo/__init__.py
excel2db/demo/generalDemoFile.py
excel2db/demo/demo1/__init__.py
excel2db/demo/demo1/demo1.py
excel2db/demo/demo10/__init__.py
excel2db/demo/demo10/demo10.py
excel2db/demo/demo11/__init__.py
excel2db/demo/demo11/demo11.py
excel2db/demo/demo2/__init__.py
excel2db/demo/demo2/demo2.py
excel2db/demo/demo3/__init__.py
excel2db/demo/demo3/demo3.py
excel2db/demo/demo4/__init__.py
excel2db/demo/demo4/demo4.py
excel2db/demo/demo5/__init__.py
excel2db/demo/demo5/demo5.py
excel2db/demo/demo6/__init__.py
excel2db/demo/demo6/demo6.py
excel2db/demo/demo7/__init__.py
excel2db/demo/demo7/demo7.py
excel2db/demo/demo8/__init__.py
excel2db/demo/demo8/demo8.py
excel2db/demo/demo9/__init__.py
excel2db/demo/demo9/demo9.py
excel2db-1.2.6.dist-info/METADATA
excel2db-1.2.6.dist-info/WHEEL
excel2db-1.2.6.dist-info/top_level.txt
excel2db-1.2.6.dist-info/RECORD
