Metadata-Version: 2.1
Name: excel2db
Version: 1.2.6
Summary: 用于将excle文件转为数据库
Home-page: https://github.com
Author: endlessdesert
Author-email: endlessdesert73@gmail.com
Requires-Dist: openpyxl
Requires-Dist: pandas
Requires-Dist: xlrd
Requires-Dist: msoffcrypto-tool
